ruamel/yaml/cmd/__init__.py
ruamel/yaml/cmd/__main__.py
ruamel/yaml/cmd/analyse.py
ruamel/yaml/cmd/generate.py
ruamel/yaml/cmd/simpleresolver.py
ruamel/yaml/cmd/yaml_cmd.py
ruamel.yaml.cmd-0.6.5.dist-info/LICENSE
ruamel.yaml.cmd-0.6.5.dist-info/METADATA
ruamel.yaml.cmd-0.6.5.dist-info/WHEEL
ruamel.yaml.cmd-0.6.5.dist-info/entry_points.txt
ruamel.yaml.cmd-0.6.5.dist-info/top_level.txt
ruamel.yaml.cmd-0.6.5.dist-info/RECORD
