Metadata-Version: 2.1
Name: ruamel.yaml.cmd
Version: 0.6.5
Summary: commandline utility to manipulate YAML files
Home-page: https://sourceforge.net/p/ruamel-yaml-cmd/code/ci/default/tree
Author: Anthon van der Neut
Author-email: a.van.der.neut@ruamel.eu
License: MIT
Classifier: Development Status :: 4 - Beta
Classifier: Intended Audience :: Developers
Classifier: License :: OSI Approved :: MIT License
Classifier: Operating System :: OS Independent
Classifier: Programming Language :: Python
Requires-Python: >=3
License-File: LICENSE
Requires-Dist: configobj
Requires-Dist: ruamel.yaml.convert (>=0.3)
Requires-Dist: ruamel.yaml (>=0.17.17)
Requires-Dist: ruamel.yaml.base
Requires-Dist: lz4
Provides-Extra: configobj
Requires-Dist: configobj ; extra == 'configobj'
